{
	"words": [
		{
			"clue": "Нож",
			"answer": "knife",
			"position": 1,
			"orientation": "across",
			"rowStart": 1,
			"colStart": 4
		},
		{
			"clue": "Салфетка",
			"answer": "napkin",
			"position": 2,
			"orientation": "down",
			"rowStart": 1,
			"colStart": 5
		},
		{
			"clue": "Вилка",
			"answer": "fork",
			"position": 3,
			"orientation": "down",
			"rowStart": 1,
			"colStart": 7
		},
		{
			"clue": "Миска",
			"answer": "bowl",
			"position": 4,
			"orientation": "down",
			"rowStart": 5,
			"colStart": 3
		},
		{
			"clue": "Ложка",
			"answer": "spoon",
			"position": 5,
			"orientation": "across",
			"rowStart": 6,
			"colStart": 1
		},
		{
			"clue": "Тарелка",
			"answer": "plate",
			"position": 6,
			"orientation": "across",
			"rowStart": 8,
			"colStart": 2
		},
		{
			"clue": "Чай",
			"answer": "tea",
			"position": 7,
			"orientation": "down",
			"rowStart": 8,
			"colStart": 5
		}
	]
}